kp_analysis_toolkit/__init__.py
kp_analysis_toolkit/cli.py
kp_analysis_toolkit/shared_funcs.py
kp_analysis_toolkit/models/__init__.py
kp_analysis_toolkit/models/base.py
kp_analysis_toolkit/nipper_expander/__init__.py
kp_analysis_toolkit/nipper_expander/cli.py
kp_analysis_toolkit/nipper_expander/process_nipper.py
kp_analysis_toolkit/nipper_expander/models/__init__.py
kp_analysis_toolkit/nipper_expander/models/program_config.py
kp_analysis_toolkit/process_scripts/__init__.py
kp_analysis_toolkit/process_scripts/cli.py
kp_analysis_toolkit/process_scripts/cli_functions.py
kp_analysis_toolkit/process_scripts/excel_exporter.py
kp_analysis_toolkit/process_scripts/file_centric_search.py
kp_analysis_toolkit/process_scripts/process_systems.py
kp_analysis_toolkit/process_scripts/search_engine.py
kp_analysis_toolkit/process_scripts/conf.d/audit-all.yaml
kp_analysis_toolkit/process_scripts/conf.d/audit-crypto-policies.yaml
kp_analysis_toolkit/process_scripts/conf.d/audit-endpoint-protection.yaml
kp_analysis_toolkit/process_scripts/conf.d/audit-file-systems.yaml
kp_analysis_toolkit/process_scripts/conf.d/audit-logging.yaml
kp_analysis_toolkit/process_scripts/conf.d/audit-network.yaml
kp_analysis_toolkit/process_scripts/conf.d/audit-remote-mgmt.yaml
kp_analysis_toolkit/process_scripts/conf.d/audit-sysinfo.yaml
kp_analysis_toolkit/process_scripts/conf.d/audit-system-services.yaml
kp_analysis_toolkit/process_scripts/conf.d/audit-time-sync.yaml
kp_analysis_toolkit/process_scripts/conf.d/audit-user-auth.yaml
kp_analysis_toolkit/process_scripts/conf.d/audit-vuln-mgmt.yaml
kp_analysis_toolkit/process_scripts/models/__init__.py
kp_analysis_toolkit/process_scripts/models/base.py
kp_analysis_toolkit/process_scripts/models/enums.py
kp_analysis_toolkit/process_scripts/models/interfaces.py
kp_analysis_toolkit/process_scripts/models/program_config.py
kp_analysis_toolkit/process_scripts/models/systems.py
kp_analysis_toolkit/process_scripts/models/topic_colors.py
kp_analysis_toolkit-2.1.0.dist-info/METADATA
kp_analysis_toolkit-2.1.0.dist-info/WHEEL
kp_analysis_toolkit-2.1.0.dist-info/entry_points.txt
kp_analysis_toolkit-2.1.0.dist-info/top_level.txt
kp_analysis_toolkit-2.1.0.dist-info/RECORD
