Metadata-Version: 2.4
Name: kp-analysis-toolkit
Version: 2.1.0
Summary: Python utilities to parse technical information for security audits
Author-email: Randy Bartels <rjbartels@outlook.com>
Project-URL: Homepage, https://github.com/kirkpatrickprice/analysis-toolkit
Project-URL: Repository, https://github.com/kirkpatrickprice/analysis-toolkit
Project-URL: Issues, https://github.com/kirkpatrickprice/analysis-toolkit/issues
Project-URL: Documentation, https://kirkpatrickprice.github.io/analysis-toolkit/
Project-URL: Changelog, https://github.com/kirkpatrickprice/analysis-toolkit/blob/main/CHANGELOG.md
Keywords: pii discovery,data discovery,credit card discovery
Classifier: Development Status :: 4 - Beta
Classifier: Intended Audience :: Information Technology
Classifier: License :: OSI Approved :: Apache Software License
Classifier: Operating System :: OS Independent
Classifier: Programming Language :: Python :: 3
Classifier: Topic :: Security
Classifier: Topic :: Utilities
Requires-Python: <4,>=3.12
Requires-Dist: charset-normalizer>=3.4.0
Requires-Dist: click>=8.1.8
Requires-Dist: openpyxl>=3.1.5
Requires-Dist: packaging>=21.0
Requires-Dist: pandas>=1.5.1
Requires-Dist: pydantic>=2.11.5
Requires-Dist: pyyaml>=6.0
Requires-Dist: rich>=14.0.0
Requires-Dist: rich-click>=1.8.0
Requires-Dist: striprtf>=0.0.26
Requires-Dist: wakepy>=0.9.0
Provides-Extra: dev
Requires-Dist: pytest>=8.3.5; extra == "dev"
Provides-Extra: docs
Requires-Dist: mkdocs>=1.6.0; extra == "docs"
Requires-Dist: mkdocs-material>=9.5.0; extra == "docs"
Requires-Dist: mkdocstrings[python]>=0.26.0; extra == "docs"
Requires-Dist: mkdocs-gen-files>=0.5.0; extra == "docs"
Requires-Dist: mkdocs-literate-nav>=0.6.0; extra == "docs"
Requires-Dist: mkdocs-section-index>=0.3.0; extra == "docs"
Requires-Dist: mkdocs-autorefs>=1.0.0; extra == "docs"
Requires-Dist: pymdown-extensions>=10.0.0; extra == "docs"
Requires-Dist: mkdocs-git-revision-date-localized-plugin>=1.2.0; extra == "docs"
Requires-Dist: mkdocs-mermaid2-plugin>=1.2.1; extra == "docs"
